G722.cpython-313-powerpc64le-linux-gnu.so
G722_debug.cpython-313-powerpc64le-linux-gnu.so
g722-1.2.2.dist-info/METADATA
g722-1.2.2.dist-info/WHEEL
g722-1.2.2.dist-info/top_level.txt
g722-1.2.2.dist-info/RECORD
g722-1.2.2.dist-info/licenses/LICENSE
