Metadata-Version: 2.1
Name: G722
Version: 1.2.2
Summary: This is a package for G.722 module
Home-page: https://github.com/sippy/libg722
Author: Maksym Sobolyev
Author-email: sobomax@sippysoft.com
License: Public-Domain
Classifier: Operating System :: OS Independent
Classifier: Programming Language :: C
Classifier: Programming Language :: Python
License-File: LICENSE
Requires-Dist: numpy
